fix_torch/__init__.py
fix_torch-0.0.3.dist-info/METADATA
fix_torch-0.0.3.dist-info/WHEEL
fix_torch-0.0.3.dist-info/top_level.txt
fix_torch-0.0.3.dist-info/RECORD
