Metadata-Version: 2.1
Name: fix-torch
Version: 0.0.3
Summary: Quality of life improvements for pytorch.
Home-page: https://github.com/Parskatt/fix_torch
Author: Johan Edstedt
Author-email: johan.edstedt@liu.se
License: UNKNOWN
Platform: UNKNOWN
Classifier: Programming Language :: Python :: 3
Classifier: License :: OSI Approved :: MIT License
Classifier: Operating System :: OS Independent
Requires-Python: >=3.6
Requires-Dist: torch
Requires-Dist: torchvision
